ipypublish/__init__.py
ipypublish/utils.py
ipypublish/bib2glossary/__init__.py
ipypublish/bib2glossary/classes.py
ipypublish/bib2glossary/definitions.py
ipypublish/bib2glossary/parse_tex.py
ipypublish/bib2glossary/test_bib2gloss.py
ipypublish/bib2glossary/test_parse_tex.py
ipypublish/convert/__init__.py
ipypublish/convert/config_manager.py
ipypublish/convert/main.py
ipypublish/convert/nbmerge.py
ipypublish/export_plugins/__init__.py
ipypublish/export_plugins/html_ipypublish_all.json
ipypublish/export_plugins/html_ipypublish_main.json
ipypublish/export_plugins/html_ipypublish_nocode.json
ipypublish/export_plugins/html_standard.json
ipypublish/export_plugins/latex_ipypublish_all.exec.json
ipypublish/export_plugins/latex_ipypublish_all.json
ipypublish/export_plugins/latex_ipypublish_main.json
ipypublish/export_plugins/latex_ipypublish_nocode.json
ipypublish/export_plugins/latex_standard_article.json
ipypublish/export_plugins/nb_ipypublish_all.json
ipypublish/export_plugins/nb_ipypublish_nocode.json
ipypublish/export_plugins/python_with_meta.json
ipypublish/export_plugins/python_with_meta_stream.json
ipypublish/export_plugins/slides_ipypublish_all.json
ipypublish/export_plugins/slides_ipypublish_main.json
ipypublish/export_plugins/slides_ipypublish_nocode.json
ipypublish/export_plugins/slides_mkdown_all.json
ipypublish/export_plugins/slides_mkdown_main.json
ipypublish/export_plugins/slides_mkdown_nocode.json
ipypublish/export_plugins/slides_standard.json
ipypublish/export_plugins/sphinx_ipypublish_all.exec.json
ipypublish/export_plugins/sphinx_ipypublish_all.ext.json
ipypublish/export_plugins/sphinx_ipypublish_all.ext.noexec.json
ipypublish/export_plugins/sphinx_ipypublish_all.json
ipypublish/export_plugins/sphinx_ipypublish_all.run.json
ipypublish/export_plugins/sphinx_ipypublish_main.json
ipypublish/export_plugins/sphinx_ipypublish_main.run.json
ipypublish/export_plugins/sphinx_ipypublish_nocode.json
ipypublish/export_plugins/sphinx_nbsphinx.json
ipypublish-0.10.12.dist-info/LICENSE
ipypublish-0.10.12.dist-info/METADATA
ipypublish-0.10.12.dist-info/WHEEL
ipypublish-0.10.12.dist-info/entry_points.txt
ipypublish-0.10.12.dist-info/top_level.txt
ipypublish-0.10.12.dist-info/zip-safe
ipypublish-0.10.12.dist-info/RECORD
