Metadata-Version: 2.1
Name: ipypublish
Version: 0.10.12
Summary: A workflow for creating and editing publication ready scientific reports, from one or more Jupyter Notebooks
Home-page: https://github.com/chrisjsewell/ipypublish
Author: Chris Sewell
Author-email: chrisj_sewell@hotmail.com
License: MIT
Keywords: python,jupyter-notebook,nbconvert,pandoc,latex,pdf
Platform: UNKNOWN
Classifier: Development Status :: 5 - Production/Stable
Classifier: Environment :: Console
Classifier: Environment :: Web Environment
Classifier: Intended Audience :: End Users/Desktop
Classifier: Intended Audience :: Science/Research
Classifier: Intended Audience :: Financial and Insurance Industry
Classifier: License :: OSI Approved :: MIT License
Classifier: Operating System :: OS Independent
Classifier: Programming Language :: Python
Classifier: Programming Language :: Python :: 3
Classifier: Programming Language :: Python :: 3.5
Classifier: Programming Language :: Python :: 3.6
Classifier: Programming Language :: Python :: 3.7
Classifier: Topic :: Scientific/Engineering
Classifier: Topic :: Software Development :: Libraries :: Python Modules
Classifier: Topic :: Utilities
Classifier: Framework :: Sphinx :: Extension
Requires-Dist: bibtexparser
Requires-Dist: jinja2
Requires-Dist: jsonextended (>=0.7)
Requires-Dist: jsonschema
Requires-Dist: jupytext
Requires-Dist: nbconvert
Requires-Dist: nbformat
Requires-Dist: ordered-set
Requires-Dist: panflute
Requires-Dist: ruamel.yaml
Requires-Dist: six (>=1.11.0)
Requires-Dist: traitlets
Requires-Dist: tornado
Requires-Dist: docutils (<0.15) ; python_version < "3"
Requires-Dist: shutilwhich ; python_version < "3.3"
Requires-Dist: pathlib2 ; python_version < "3.4"
Requires-Dist: typing ; python_version < "3.5"
Requires-Dist: docutils ; python_version >= "3"
Provides-Extra: code_style
Requires-Dist: black (==19.3b0) ; extra == 'code_style'
Requires-Dist: pre-commit (==1.17.0) ; extra == 'code_style'
Requires-Dist: flake8 (<3.8.0,>=3.7.0) ; extra == 'code_style'
Requires-Dist: doc8 (<0.9.0,>=0.8.0) ; extra == 'code_style'
Requires-Dist: pygments ; extra == 'code_style'
Provides-Extra: rtd
Requires-Dist: numpy ; extra == 'rtd'
Requires-Dist: sympy (<1.3) ; extra == 'rtd'
Requires-Dist: recommonmark (>=0.5) ; extra == 'rtd'
Requires-Dist: sphinxcontrib-bibtex ; extra == 'rtd'
Requires-Dist: ipykernel ; extra == 'rtd'
Requires-Dist: pytest (>=4.4) ; extra == 'rtd'
Requires-Dist: ipywidgets (<8,>=7.5) ; extra == 'rtd'
Requires-Dist: matplotlib ; extra == 'rtd'
Requires-Dist: pandas ; extra == 'rtd'
Requires-Dist: pillow ; extra == 'rtd'
Requires-Dist: sphinx (>=1.8) ; extra == 'rtd'
Provides-Extra: science
Requires-Dist: numpy ; extra == 'science'
Requires-Dist: sympy ; extra == 'science'
Requires-Dist: matplotlib ; extra == 'science'
Requires-Dist: pandas ; extra == 'science'
Provides-Extra: sphinx
Requires-Dist: sphinxcontrib-bibtex ; extra == 'sphinx'
Requires-Dist: sphinx (>=1.8) ; extra == 'sphinx'
Provides-Extra: tests
Requires-Dist: coverage ; extra == 'tests'
Requires-Dist: texsoup (<=0.1.4) ; extra == 'tests'
Requires-Dist: sphinxcontrib-bibtex ; extra == 'tests'
Requires-Dist: ipykernel ; extra == 'tests'
Requires-Dist: pytest-regressions ; extra == 'tests'
Requires-Dist: sphinx (<3,>=1.6) ; extra == 'tests'
Requires-Dist: pytest (>=3.6) ; extra == 'tests'
Requires-Dist: pillow ; extra == 'tests'
Requires-Dist: nbsphinx (<0.6,>=0.5) ; extra == 'tests'
Requires-Dist: pytest-cov ; extra == 'tests'
